<Properties StartupConfiguration="{7B6D6ADF-7C1C-404C-9935-7A74A332D80C}|Default">
  <MonoDevelop.Ide.Workbench>
    <Files>
      <File FileName="Mission1/wwwroot/index.html" Line="43" Column="44" />
      <File FileName="Mission1/wwwroot/css/styles.css" Line="8" Column="18" />
    </Files>
    <Pads>
      <Pad Id="ProjectPad">
        <State name="__root__">
          <Node name="Mission1" expanded="True">
            <Node name="Mission1" expanded="True">
              <Node name="wwwroot" expanded="True">
                <Node name="css" expanded="True" />
                <Node name="js" expanded="True" />
                <Node name="lib" expanded="True">
                  <Node name="bootstrap" expanded="True" />
                  <Node name="jquery" expanded="True" />
                </Node>
                <Node name="index.html" selected="True" />
              </Node>
            </Node>
          </Node>
        </State>
      </Pad>
    </Pads>
  </MonoDevelop.Ide.Workbench>
  <MonoDevelop.Ide.DebuggingService.PinnedWatches />
  <MonoDevelop.Ide.Workspace ActiveConfiguration="Debug" />
  <MonoDevelop.Ide.ItemProperties.Mission1 PreferredExecutionTarget="/Applications/Google Chrome.app" />
  <MonoDevelop.Ide.DebuggingService.Breakpoints>
    <BreakpointStore />
  </MonoDevelop.Ide.DebuggingService.Breakpoints>
  <MultiItemStartupConfigurations />
</Properties>